{
  "fps": 30,
  "totalFrames": 4117,
  "width": 1080,
  "height": 1920,
  "format": "shorts",
  "scenes": [
    {
      "id": "scene_1",
      "type": "hook",
      "startFrame": 0,
      "endFrame": 320,
      "durationFrames": 320,
      "cursorKeyframes": [
        {
          "frame": 60,
          "x": 540,
          "y": 960,
          "action": "move",
          "target": "broken-route-string"
        }
      ]
    },
    {
      "id": "scene_2",
      "type": "problem",
      "startFrame": 320,
      "endFrame": 699,
      "durationFrames": 379,
      "cursorKeyframes": [
        {
          "frame": 440,
          "x": 310,
          "y": 420,
          "action": "highlight",
          "target": "string-type"
        },
        {
          "frame": 560,
          "x": 420,
          "y": 850,
          "action": "move",
          "target": "typo-route"
        }
      ]
    },
    {
      "id": "scene_3",
      "type": "explanation",
      "startFrame": 699,
      "endFrame": 1071,
      "durationFrames": 372,
      "cursorKeyframes": [
        {
          "frame": 789,
          "x": 520,
          "y": 380,
          "action": "move",
          "target": "template-literal-definition"
        }
      ]
    },
    {
      "id": "scene_4",
      "type": "code",
      "startFrame": 1071,
      "endFrame": 1481,
      "durationFrames": 410,
      "cursorKeyframes": [
        {
          "frame": 1191,
          "x": 680,
          "y": 420,
          "action": "highlight",
          "target": "infer-syntax"
        },
        {
          "frame": 1371,
          "x": 610,
          "y": 510,
          "action": "move",
          "target": "recursive-call"
        }
      ]
    },
    {
      "id": "scene_5",
      "type": "explanation",
      "startFrame": 1481,
      "endFrame": 1893,
      "durationFrames": 412,
      "cursorKeyframes": []
    },
    {
      "id": "scene_6",
      "type": "code",
      "startFrame": 1893,
      "endFrame": 2285,
      "durationFrames": 392,
      "cursorKeyframes": [
        {
          "frame": 1983,
          "x": 380,
          "y": 420,
          "action": "highlight",
          "target": "const-generic"
        },
        {
          "frame": 2163,
          "x": 420,
          "y": 610,
          "action": "move",
          "target": "params-argument"
        }
      ]
    },
    {
      "id": "scene_7",
      "type": "demo",
      "startFrame": 2285,
      "endFrame": 2649,
      "durationFrames": 364,
      "cursorKeyframes": [
        {
          "frame": 2435,
          "x": 450,
          "y": 800,
          "action": "click",
          "target": "autocomplete-popup"
        }
      ]
    },
    {
      "id": "scene_8",
      "type": "code",
      "startFrame": 2649,
      "endFrame": 2992,
      "durationFrames": 343,
      "cursorKeyframes": [
        {
          "frame": 2829,
          "x": 380,
          "y": 750,
          "action": "move",
          "target": "error-squiggly"
        }
      ]
    },
    {
      "id": "scene_9",
      "type": "explanation",
      "startFrame": 2992,
      "endFrame": 3389,
      "durationFrames": 397,
      "cursorKeyframes": []
    },
    {
      "id": "scene_10",
      "type": "summary",
      "startFrame": 3389,
      "endFrame": 3809,
      "durationFrames": 420,
      "cursorKeyframes": []
    },
    {
      "id": "scene_11",
      "type": "outro",
      "startFrame": 3809,
      "endFrame": 4117,
      "durationFrames": 308,
      "cursorKeyframes": [
        {
          "frame": 3899,
          "x": 540,
          "y": 1200,
          "action": "click",
          "target": "subscribe-button"
        }
      ]
    }
  ]
}